MANIFEST.in
README.md
setup.cfg
setup.py
versioneer.py
azotea/__init__.py
azotea/__main__.py
azotea/_version.py
azotea/backup.py
azotea/camera.py
azotea/cfgcmds.py
azotea/changed.py
azotea/config.py
azotea/database.py
azotea/exceptions.py
azotea/image.py
azotea/reorg.py
azotea/session.py
azotea/utils.py
azotea.egg-info/PKG-INFO
azotea.egg-info/SOURCES.txt
azotea.egg-info/dependency_links.txt
azotea.egg-info/requires.txt
azotea.egg-info/top_level.txt
azotea/data/azotea.ini
azotea/data/camera.ini
azotea/data/sql/purge.sql
azotea/data/sql/schema.sql
azotea/data/sql/data/auxiliar.sql
azotenodo/__init__.py
azotenodo/__main__.py
azotenodo/config.py
azotenodo/exceptions.py
azotenodo/packer.py
azotenodo/zenodo.py
azotenodo/data/azotenodo.ini
files/azotea
files/migrate_hash