Metadata-Version: 2.1
Name: azotea
Version: 0.3.39
Summary: ('command line tool to reduce DSLR RAW images',)
Home-page: https://guaix.ucm.es/AZOTEA
Author: Rafael González
Author-email: astrorafael@gmail.com
License: MIT
Keywords: Astronomy Python LightPollution
Platform: UNKNOWN
Classifier: Environment :: Console
Classifier: Intended Audience :: Science/Research
Classifier: Intended Audience :: Developers
Classifier: License :: OSI Approved :: MIT License
Classifier: Operating System :: POSIX :: Linux
Classifier: Programming Language :: Python :: 3.6
Classifier: Topic :: Scientific/Engineering :: Astronomy
Classifier: Topic :: Scientific/Engineering :: Atmospheric Science
Classifier: Development Status :: 4 - Beta
